[
  {
    "content": "#1 XSS — ✅ already fixed with DOMPurify (verified)",
    "status": "completed"
  },
  {
    "content": "#3 Fix empty catch blocks — both now log via console.warn with context",
    "status": "completed"
  },
  {
    "content": "#5 useMemo on context values — ThemeContext, AuthContext, BillingContext",
    "status": "completed"
  },
  {
    "content": "#8 console statements — ZERO console.log; all are legitimate error handlers",
    "status": "completed"
  },
  {
    "content": "#2 Hook deps — verified ZERO real exhaustive-deps violations (false positives)",
    "status": "completed"
  },
  {
    "content": "#7 Python `is`/`==` — verified all 15 are correct `is None` per PEP 8 (false positives)",
    "status": "completed"
  },
  {
    "content": "#4 Token storage — already documented in AuthContext.jsx as intentional trade-off",
    "status": "completed"
  },
  {
    "content": "#6 Big refactors (DocumentEditor, ReminderTemplates, build_extras_router, attach_ai_routes) — deferred",
    "status": "completed"
  }
]